tests/__init__.py
tests/test_multiplication.py
multiply_internship_2024-0.1.dist-info/METADATA
multiply_internship_2024-0.1.dist-info/WHEEL
multiply_internship_2024-0.1.dist-info/top_level.txt
multiply_internship_2024-0.1.dist-info/RECORD
