Metadata-Version: 2.1
Name: multiply_internship_2024
Version: 0.1
Summary: Description of your package
Author: Abdallah Abdelsameia
Author-email: aabdelsameia1@gmail.com
Classifier: Programming Language :: Python :: 3
Classifier: License :: OSI Approved :: MIT License
Classifier: Operating System :: OS Independent
Requires-Python: >=3.6
